gbox/__init__.py
gbox/client.py
gbox/config.py
gbox/exceptions.py
gbox/api/__init__.py
gbox/api/box_api.py
gbox/api/client.py
gbox/api/file_api.py
gbox/managers/__init__.py
gbox/managers/boxes.py
gbox/managers/files.py
gbox/models/__init__.py
gbox/models/boxes.py
gbox/models/files.py
pygbox-0.0.3.dist-info/licenses/LICENSE
pygbox-0.0.3.dist-info/METADATA
pygbox-0.0.3.dist-info/WHEEL
pygbox-0.0.3.dist-info/top_level.txt
pygbox-0.0.3.dist-info/RECORD
