Metadata-Version: 2.4
Name: pygbox
Version: 0.0.3
Summary: Official Python SDK for GBox API
Home-page: https://github.com/babelcloud/gbox
Author: Gru.ai
License-Expression: Apache-2.0
Requires-Python: >=3.7
License-File: LICENSE
Requires-Dist: requests>=2.25.0
Requires-Dist: pydantic>=2.0
Provides-Extra: dev
Requires-Dist: pytest>=7.0.0; extra == "dev"
Requires-Dist: pytest-mock>=3.8.0; extra == "dev"
Requires-Dist: pytest-cov>=4.0.0; extra == "dev"
Requires-Dist: black>=21.5b2; extra == "dev"
Requires-Dist: mypy>=0.812; extra == "dev"
Requires-Dist: ruff>=0.1.0; extra == "dev"
Requires-Dist: isort>=5.10.0; extra == "dev"
Dynamic: license-file
